LICENSE
MANIFEST.in
README.md
setup.cfg
setup.py
docs/Makefile
docs/authors.rst
docs/conf.py
docs/contributing.rst
docs/history.rst
docs/index.rst
docs/installation.rst
docs/make.bat
docs/readme.rst
docs/usage.rst
enjoy/__init__.py
enjoy/_input.py
enjoy/cli.py
enjoy/enjoy.py
enjoy/gencodes.py
enjoy/input.py
enjoy.egg-info/PKG-INFO
enjoy.egg-info/SOURCES.txt
enjoy.egg-info/dependency_links.txt
enjoy.egg-info/requires.txt
enjoy.egg-info/top_level.txt
enjoy.egg-info/zip-safe
tests/test_enjoy.py