Metadata-Version: 2.1
Name: enjoy
Version: 0.1.2
Summary: I/O agnostic approach to linux input system
Home-page: https://github.com/tiagocoutinho/enjoy
Author: Jose Tiago Macara Coutinho
Author-email: coutinhotiago@gmail.com
License: GPLv3
Project-URL: Documentation, https://github.com/tiagocoutinho/enjoy
Project-URL: Source, https://github.com/tiagocoutinho/enjoy
Keywords: enjoy,input,joystick,gamepad,linux
Platform: UNKNOWN
Classifier: Development Status :: 2 - Pre-Alpha
Classifier: Intended Audience :: Developers
Classifier: License :: OSI Approved :: GNU General Public License v3 (GPLv3)
Classifier: Natural Language :: English
Classifier: Programming Language :: Python :: 3
Classifier: Programming Language :: Python :: 3.7
Requires-Python: >=3.5
